Workbook

Sheet Monthly Data
A1: Month | B1: Income | C1: Rent | D1: Groceries | E1: Electricity | F1: Transport | G1: Medical | H1: Entertainment | I1: Clothing | J1: Misc | K1: Total Expense | L1: Savings | M1: Savings %
A2: January | B2: 28500 | C2: 8000 | D2: 4200 | E2: 1850 | F2: 1500 | G2: 0 | H2: 800 | I2: 0 | J2: 600 | K2: =SUM(C2:J2) -> 16950 | L2: =B2-K2 -> 11550 | M2: =IF(B2>0,L2/B2,0) -> 0.40526316
A3: February | B3: 28500 | C3: 8000 | D3: 3900 | E3: 1600 | F3: 1500 | G3: 500 | H3: 600 | I3: 1200 | J3: 450 | K3: =SUM(C3:J3) -> 17750 | L3: =B3-K3 -> 10750 | M3: =IF(B3>0,L3/B3,0) -> 0.37719298
A4: March | B4: 28500 | C4: 8000 | D4: 4100 | E4: 1500 | F4: 1500 | G4: 0 | H4: 700 | I4: 0 | J4: 300 | K4: =SUM(C4:J4) -> 16100 | L4: =B4-K4 -> 12400 | M4: =IF(B4>0,L4/B4,0) -> 0.43508772
A5: April | B5: 29000 | C5: 8000 | D5: 4500 | E5: 2100 | F5: 1500 | G5: 800 | H5: 1000 | I5: 0 | J5: 500 | K5: =SUM(C5:J5) -> 18400 | L5: =B5-K5 -> 10600 | M5: =IF(B5>0,L5/B5,0) -> 0.36551724
A6: May | B6: 29000 | C6: 8000 | D6: 4800 | E6: 2500 | F6: 1500 | G6: 0 | H6: 900 | I6: 2500 | J6: 400 | K6: =SUM(C6:J6) -> 20600 | L6: =B6-K6 -> 8400 | M6: =IF(B6>0,L6/B6,0) -> 0.28965517
A7: June | B7: 29000 | C7: 8000 | D7: 4300 | E7: 2200 | F7: 1500 | G7: 300 | H7: 500 | I7: 0 | J7: 350 | K7: =SUM(C7:J7) -> 17150 | L7: =B7-K7 -> 11850 | M7: =IF(B7>0,L7/B7,0) -> 0.40862069
A8: July | B8: 29500 | C8: 8000 | D8: 5000 | E8: 1800 | F8: 1600 | G8: 0 | H8: 600 | I8: 0 | J8: 700 | K8: =SUM(C8:J8) -> 17700 | L8: =B8-K8 -> 11800 | M8: =IF(B8>0,L8/B8,0) -> 0.4
A9: August | B9: 29500 | C9: 8000 | D9: 4700 | E9: 1750 | F9: 1600 | G9: 1200 | H9: 800 | I9: 1800 | J9: 500 | K9: =SUM(C9:J9) -> 20350 | L9: =B9-K9 -> 9150 | M9: =IF(B9>0,L9/B9,0) -> 0.31016949
A10: September | B10: 29500 | C10: 8000 | D10: 4400 | E10: 1700 | F10: 1600 | G10: 0 | H10: 1200 | I10: 3000 | J10: 600 | K10: =SUM(C10:J10) -> 20500 | L10: =B10-K10 -> 9000 | M10: =IF(B10>0,L10/B10,0) -> 0.30508475
A11: October | B11: 30000 | C11: 8000 | D11: 5200 | E11: 1600 | F11: 1600 | G11: 0 | H11: 1500 | I11: 2000 | J11: 800 | K11: =SUM(C11:J11) -> 20700 | L11: =B11-K11 -> 9300 | M11: =IF(B11>0,L11/B11,0) -> 0.31
A12: November | B12: 30000 | C12: 8000 | D12: 5000 | E12: 1900 | F12: 1600 | G12: 600 | H12: 1800 | I12: 1500 | J12: 700 | K12: =SUM(C12:J12) -> 21100 | L12: =B12-K12 -> 8900 | M12: =IF(B12>0,L12/B12,0) -> 0.29666667
A13: December | B13: 30000 | C13: 8000 | D13: 5500 | E13: 2000 | F13: 1600 | G13: 0 | H13: 2500 | I13: 1000 | J13: 900 | K13: =SUM(C13:J13) -> 21500 | L13: =B13-K13 -> 8500 | M13: =IF(B13>0,L13/B13,0) -> 0.28333333
A14: TOTAL | B14: =SUM(B2:B13) -> 351000 | C14: =SUM(C2:C13) -> 96000 | D14: =SUM(D2:D13) -> 55600 | E14: =SUM(E2:E13) -> 22500 | F14: =SUM(F2:F13) -> 18600 | G14: =SUM(G2:G13) -> 3400 | H14: =SUM(H2:H13) -> 12900 | I14: =SUM(I2:I13) -> 13000 | ... L14: =SUM(L2:L13) -> 122200 | M14: =IF(B14>0,L14/B14,0) -> 0.34814815

Sheet Pivot Analysis
A1: 📊 HOUSEHOLD BUDGET — PIVOT ANALYSIS 2025
A3: Monthly Income vs Expense vs Savings | F3: Category-wise Annual Expense
A4: Month | B4: Income (₹) | C4: Total Expense (₹) | D4: Savings (₹) | F4: Category | G4: Annual Total (₹) | H4: Share %
A5: ='Monthly Data'!A3 -> February | B5: ='Monthly Data'!B3 -> 28500 | C5: ='Monthly Data'!K3 -> 17750 | D5: ='Monthly Data'!L3 -> 10750 | F5: Rent | G5: =SUM('Monthly Data'!C2:'Monthly Data'!C13) -> 96000 | H5: =IF(G5>0,G5/SUM($G$5:$G$12),0) -> 0.41958042
A6: ='Monthly Data'!A4 -> March | B6: ='Monthly Data'!B4 -> 28500 | C6: ='Monthly Data'!K4 -> 16100 | D6: ='Monthly Data'!L4 -> 12400 | F6: Groceries | G6: =SUM('Monthly Data'!D2:'Monthly Data'!D13) -> 55600 | H6: =IF(G6>0,G6/SUM($G$5:$G$12),0) -> 0.24300699
A7: ='Monthly Data'!A5 -> April | B7: ='Monthly Data'!B5 -> 29000 | C7: ='Monthly Data'!K5 -> 18400 | D7: ='Monthly Data'!L5 -> 10600 | F7: Electricity | G7: =SUM('Monthly Data'!E2:'Monthly Data'!E13) -> 22500 | H7: =IF(G7>0,G7/SUM($G$5:$G$12),0) -> 0.098339161
A8: ='Monthly Data'!A6 -> May | B8: ='Monthly Data'!B6 -> 29000 | C8: ='Monthly Data'!K6 -> 20600 | D8: ='Monthly Data'!L6 -> 8400 | F8: Transport | G8: =SUM('Monthly Data'!F2:'Monthly Data'!F13) -> 18600 | H8: =IF(G8>0,G8/SUM($G$5:$G$12),0) -> 0.081293706
A9: ='Monthly Data'!A7 -> June | B9: ='Monthly Data'!B7 -> 29000 | C9: ='Monthly Data'!K7 -> 17150 | D9: ='Monthly Data'!L7 -> 11850 | F9: Medical | G9: =SUM('Monthly Data'!G2:'Monthly Data'!G13) -> 3400 | H9: =IF(G9>0,G9/SUM($G$5:$G$12),0) -> 0.01486014
A10: ='Monthly Data'!A8 -> July | B10: ='Monthly Data'!B8 -> 29500 | C10: ='Monthly Data'!K8 -> 17700 | D10: ='Monthly Data'!L8 -> 11800 | F10: Entertainment | G10: =SUM('Monthly Data'!H2:'Monthly Data'!H13) -> 12900 | H10: =IF(G10>0,G10/SUM($G$5:$G$12),0) -> 0.056381119
A11: ='Monthly Data'!A9 -> August | B11: ='Monthly Data'!B9 -> 29500 | C11: ='Monthly Data'!K9 -> 20350 | D11: ='Monthly Data'!L9 -> 9150 | F11: Clothing | G11: =SUM('Monthly Data'!I2:'Monthly Data'!I13) -> 13000 | H11: =IF(G11>0,G11/SUM($G$5:$G$12),0) -> 0.056818182
A12: ='Monthly Data'!A10 -> September | B12: ='Monthly Data'!B10 -> 29500 | C12: ='Monthly Data'!K10 -> 20500 | D12: ='Monthly Data'!L10 -> 9000 | F12: Misc | G12: =SUM('Monthly Data'!J2:'Monthly Data'!J13) -> 6800 | H12: =IF(G12>0,G12/SUM($G$5:$G$12),0) -> 0.02972028
A13: ='Monthly Data'!A11 -> October | B13: ='Monthly Data'!B11 -> 30000 | C13: ='Monthly Data'!K11 -> 20700 | D13: ='Monthly Data'!L11 -> 9300 | F13: TOTAL | G13: =SUM(G5:G12) -> 228800 | H13: 100.0%
A14: ='Monthly Data'!A12 -> November | B14: ='Monthly Data'!B12 -> 30000 | C14: ='Monthly Data'!K12 -> 21100 | D14: ='Monthly Data'!L12 -> 8900
A15: ='Monthly Data'!A13 -> December | B15: ='Monthly Data'!B13 -> 30000 | C15: ='Monthly Data'!K13 -> 21500 | D15: ='Monthly Data'!L13 -> 8500
A16: ='Monthly Data'!A14 -> TOTAL | B16: ='Monthly Data'!B14 -> 351000 | C16: ='Monthly Data'!K14 -> 228800 | D16: ='Monthly Data'!L14 -> 122200
A17: TOTAL | B17: =SUM(B5:B16) -> 673500 | C17: =SUM(C5:C16) -> 440650 | D17: =SUM(D5:D16) -> 232850
D20: Quarterly Summary
D21: Quarter | E21: Income (₹) | F21: Expense (₹) | G21: Savings (₹)
D22: Q1 (Jan-Mar) | E22: =SUM('Monthly Data'!B2:B4) -> 85500 | F22: =SUM('Monthly Data'!K2:K4) -> 50800 | G22: =SUM('Monthly Data'!L2:L4) -> 34700
D23: Q2 (Apr-Jun) | E23: =SUM('Monthly Data'!B5:B7) -> 87000 | F23: =SUM('Monthly Data'!K5:K7) -> 56150 | G23: =SUM('Monthly Data'!L5:L7) -> 30850
D24: Q3 (Jul-Sep) | E24: =SUM('Monthly Data'!B8:B10) -> 88500 | F24: =SUM('Monthly Data'!K8:K10) -> 58550 | G24: =SUM('Monthly Data'!L8:L10) -> 29950
D25: Q4 (Oct-Dec) | E25: =SUM('Monthly Data'!B11:B13) -> 90000 | F25: =SUM('Monthly Data'!K11:K13) -> 63300 | G25: =SUM('Monthly Data'!L11:L13) -> 26700

Sheet Dashboard
A1: 🏠 HOUSEHOLD BUDGET DASHBOARD — 2025
A4: 💰 Total Income | E4: 💸 Total Expense | I4: 🏦 Total Savings | M4: 📈 Savings Rate | Q4: 📅 Best Month
A6: =SUM('Monthly Data'!B2:B13) -> 351000 | E6: =SUM('Monthly Data'!K2:K13) -> 228800 | I6: =SUM('Monthly Data'!L2:L13) -> 122200 | M6: =SUM('Monthly Data'!L2:L13)/SUM('Monthly Data'!B2:B13) -> 0.34814815 | Q6: {=INDEX('Monthly Data'!A2:A13,MATCH(MAX('Monthly Data'!L2:L13),'Monthly Data'!L2:L13,0))} -> March
